{"errors":[],"warnings":[],"namedChunkGroups":{"polyfill":{"chunks":[1,4],"assets":["webpack-runtime-edd43c1b92e4425ffc46.js","webpack-runtime-edd43c1b92e4425ffc46.js.map","polyfill-22037781de1e4806f3e2.js","polyfill-22037781de1e4806f3e2.js.map"],"children":{},"childAssets":{}},"app":{"chunks":[1,0,3,2],"assets":["webpack-runtime-edd43c1b92e4425ffc46.js","webpack-runtime-edd43c1b92e4425ffc46.js.map","styles.efe32882dd99b430f109.css","styles-407fe62976dc5310c43e.js","styles-407fe62976dc5310c43e.js.map","framework-2e650e46695fe483e136.js","framework-2e650e46695fe483e136.js.map","app-ceac74d5503b97c585e4.js","app-ceac74d5503b97c585e4.js.map"],"children":{},"childAssets":{}}},"assetsByChunkName":{"polyfill":["webpack-runtime-edd43c1b92e4425ffc46.js","polyfill-22037781de1e4806f3e2.js"],"app":["webpack-runtime-edd43c1b92e4425ffc46.js","styles.efe32882dd99b430f109.css","styles-407fe62976dc5310c43e.js","framework-2e650e46695fe483e136.js","app-ceac74d5503b97c585e4.js"]}}